lowbar/__init__.py
lowbar-2.2.1.dist-info/METADATA
lowbar-2.2.1.dist-info/WHEEL
lowbar-2.2.1.dist-info/licenses/LICENSE
lowbar-2.2.1.dist-info/RECORD
