Metadata-Version: 2.3
Name: lowbar
Version: 2.2.1
Summary: The simplest no-nonsense progress bar for python.
Project-URL: Homepage, https://github.com/AnnikaV9/lowbar
Project-URL: Repository, https://github.com/AnnikaV9/lowbar
Project-URL: Bug Tracker, https://github.com/AnnikaV9/lowbar/issues
Project-URL: Changelog, https://github.com/AnnikaV9/lowbar/releases
Author-email: AnnikaV9 <carrot.moncher@gmail.com>
License-Expression: MIT
License-File: LICENSE
Classifier: Intended Audience :: Developers
Classifier: Intended Audience :: Education
Classifier: Intended Audience :: End Users/Desktop
Classifier: Intended Audience :: Other Audience
Classifier: Intended Audience :: System Administrators
Classifier: License :: OSI Approved :: MIT License
Classifier: Operating System :: OS Independent
Classifier: Programming Language :: Python :: 3
Classifier: Topic :: Software Development :: Build Tools
Classifier: Topic :: Software Development :: Libraries
Classifier: Topic :: Software Development :: Libraries :: Python Modules
Classifier: Topic :: Software Development :: User Interfaces
Classifier: Topic :: System :: Installation/Setup
Classifier: Topic :: System :: Logging
Classifier: Topic :: System :: Monitoring
Classifier: Topic :: System :: Shells
Classifier: Topic :: Terminals
Classifier: Topic :: Utilities
Requires-Python: >=3.7
